st_dataframe_component/__init__.py
st_dataframe_component/frontend/build/asset-manifest.json
st_dataframe_component/frontend/build/index.html
st_dataframe_component/frontend/build/style.css
st_dataframe_component/frontend/build/vite.svg
st_dataframe_component/frontend/build/static/js/2.787c6e0f.chunk.js
st_dataframe_component/frontend/build/static/js/2.787c6e0f.chunk.js.LICENSE.txt
st_dataframe_component/frontend/build/static/js/2.787c6e0f.chunk.js.map
st_dataframe_component/frontend/build/static/js/main.ad62b15e.chunk.js
st_dataframe_component/frontend/build/static/js/main.ad62b15e.chunk.js.map
st_dataframe_component/frontend/build/static/js/runtime-main.3cd58270.js
st_dataframe_component/frontend/build/static/js/runtime-main.3cd58270.js.map
st_dataframe_component-0.0.5.dist-info/METADATA
st_dataframe_component-0.0.5.dist-info/WHEEL
st_dataframe_component-0.0.5.dist-info/top_level.txt
st_dataframe_component-0.0.5.dist-info/RECORD
