Metadata-Version: 2.1
Name: st-dataframe-component
Version: 0.0.5
Home-page: 
Author: MrYasuo
Author-email: 
Requires-Python: >=3.6
Requires-Dist: streamlit (>=0.63)
